pybotx_fsm/__init__.py
pybotx_fsm/collector.py
pybotx_fsm/fsm.py
pybotx_fsm/middleware.py
pybotx_fsm/py.typed
pybotx_fsm/state_repo_proto.py
pybotx_fsm/templates.py
pybotx_fsm-0.6.1.dist-info/LICENSE.md
pybotx_fsm-0.6.1.dist-info/METADATA
pybotx_fsm-0.6.1.dist-info/WHEEL
pybotx_fsm-0.6.1.dist-info/RECORD
