Metadata-Version: 2.3
Name: pybotx-fsm
Version: 0.6.1
Summary: FSM middleware for using with pybotx
Requires-Python: >=3.9,<3.14
Classifier: Programming Language :: Python :: 3
Classifier: Programming Language :: Python :: 3.9
Classifier: Programming Language :: Python :: 3.10
Classifier: Programming Language :: Python :: 3.11
Classifier: Programming Language :: Python :: 3.12
Classifier: Programming Language :: Python :: 3.13
Requires-Dist: pybotx (>=0.75.0)
